superrad/__init__.py
superrad/boson_couplings.py
superrad/boson_waveform.py
superrad/cloud_model.py
superrad/evolve_cloud.py
superrad/full_evo_waveform.py
superrad/geometry.py
superrad/geometry_model.py
superrad/harmonics.py
superrad/hybrid_cloud.py
superrad/interp_freq_shift.py
superrad/kerr_geometry.py
superrad/matched_waveform.py
superrad/nonrel_cloud.py
superrad/orbit_dynamics.py
superrad/rel_sca_cloud.py
superrad/rel_vec_cloud.py
superrad/spin_down.py
superrad/ultralight_boson.py
superrad/units.py
superrad/data/m1_pr_mds.npz
superrad/data/m1_sc_mds.npz
superrad/data/m2_pr_mds.npz
superrad/data/m2_sc_mds.npz
superrad/data/m3_pr_mds.npz
superrad/data/m4_pr_mds.npz
superrad/data/m5_pr_mds.npz
superrad/data/pr_fits.npz
superrad/data/pr_fits_higher_m.npz
superrad/data/pr_sat_gw.npz
superrad/data/sc_fits.npz
superrad/data/sc_sat_gw.npz
superrad/data/scalar_freqshift_m1.npz
superrad/data/scalar_freqshift_m1_ha.npz
superrad/data/scalar_freqshift_m1_interp.npz
superrad/data/scalar_freqshift_m1_la.npz
superrad/data/scalar_geometry.npz
superrad/data/scalar_geometry_errors.npz
superrad/data/spin2_omega.dat
superrad/data/vector_freqshift_error.npz
superrad/data/vector_freqshift_error_ha.npz
superrad/data/vector_freqshift_error_la.npz
superrad/data/vector_freqshift_m1_ha.npz
superrad/data/vector_freqshift_m1_interp.npz
superrad/data/vector_freqshift_m1_la.npz
superrad/data/vector_freqshift_m1_ma.npz
superrad/data/vector_geometry.npz
superrad/data/vector_geometry_errors.npz
superrad-0.3.0.dist-info/licenses/LICENSE
superrad-0.3.0.dist-info/METADATA
superrad-0.3.0.dist-info/WHEEL
superrad-0.3.0.dist-info/top_level.txt
superrad-0.3.0.dist-info/RECORD
