Metadata-Version: 2.4
Name: superrad
Version: 0.3.0
Summary: Model black hole superradiance
Project-URL: Homepage, https://www.bitbucket.org/weast/superrad
Project-URL: Bug Tracker, https://www.bitbucket.org/weast/superrad/issues
Classifier: Programming Language :: Python :: 3
Classifier: License :: OSI Approved :: BSD License
Classifier: Operating System :: OS Independent
Requires-Python: >=3.4
License-File: LICENSE
Requires-Dist: numpy
Requires-Dist: scipy
Provides-Extra: examples
Requires-Dist: matplotlib; extra == "examples"
Dynamic: license-file
